topsis/__init__.py
topsis/topsis.py
topsis_parth_102216063/__init__.py
topsis_parth_102216063/topsis.py
Topsis_Parth_102216063-0.1.dist-info/License
Topsis_Parth_102216063-0.1.dist-info/METADATA
Topsis_Parth_102216063-0.1.dist-info/WHEEL
Topsis_Parth_102216063-0.1.dist-info/top_level.txt
Topsis_Parth_102216063-0.1.dist-info/RECORD
